[
    {
        "N. DDT":  "260040",
        "Data":  "17/04/2026",
        "Cod. Fornitore":  "F050748",
        "Fornitore":  "ACCIAIO T. \u0026 D. SRL",
        "Importo":  "2982.600000",
        "Note":  "CANNAZZARO BRUTIUM e ACAL Basato su Ordini d\u0027acquisto 260009. 260057."
    },
    {
        "N. DDT":  "260034",
        "Data":  "15/04/2026",
        "Cod. Fornitore":  "F051522",
        "Fornitore":  "MODULAR PROFESSIONAL srl",
        "Importo":  "239.120000",
        "Note":  "DETERGENTE Basato su Ordini d\u0027acquisto 260030."
    },
    {
        "N. DDT":  "260033",
        "Data":  "08/04/2026",
        "Cod. Fornitore":  "F000894",
        "Fornitore":  "COLDLINE srl",
        "Importo":  "8972.650000",
        "Note":  "CORRADO MICHELA E MeM Basato su Ordini d\u0027acquisto 260013. 260018."
    }
]